yatagan/__init__.py
yatagan/yatagan.py
Yatagan-0.0.1.dist-info/LICENSE
Yatagan-0.0.1.dist-info/METADATA
Yatagan-0.0.1.dist-info/WHEEL
Yatagan-0.0.1.dist-info/top_level.txt
Yatagan-0.0.1.dist-info/RECORD
