Metadata-Version: 2.1
Name: Yatagan
Version: 0.0.1
Summary: A package to make CTFs easier
Home-page: https://github.com/ahmedselim2017/yatagan
Author: Ahmed Selim Üzüm
Author-email: ahmedselimuzum@gmail.com
License: UNKNOWN
Platform: UNKNOWN
Classifier: Programming Language :: Python :: 3.8
Classifier: License :: OSI Approved :: GNU General Public License v3 (GPLv3)
